{"nodes": [{"id": "c_new_drive_data_project_tester_cost_manager_expenser_graph_system_graph_json", "label": "system_graph.json", "file_type": "code", "source_file": "C:\\New Drive Data\\Project Tester - Cost Manager & Expenser\\graph\\system_graph.json", "source_location": "L1"}, {"id": "graph_system_graph_ledger", "label": "Ledger", "file_type": "code", "source_file": "C:\\New Drive Data\\Project Tester - Cost Manager & Expenser\\graph\\system_graph.json", "source_location": "L2"}, {"id": "graph_system_graph_wallet", "label": "Wallet", "file_type": "code", "source_file": "C:\\New Drive Data\\Project Tester - Cost Manager & Expenser\\graph\\system_graph.json", "source_location": "L3"}, {"id": "graph_system_graph_loans", "label": "Loans", "file_type": "code", "source_file": "C:\\New Drive Data\\Project Tester - Cost Manager & Expenser\\graph\\system_graph.json", "source_location": "L4"}, {"id": "graph_system_graph_analytics", "label": "Analytics", "file_type": "code", "source_file": "C:\\New Drive Data\\Project Tester - Cost Manager & Expenser\\graph\\system_graph.json", "source_location": "L5"}, {"id": "graph_system_graph_forecast", "label": "Forecast", "file_type": "code", "source_file": "C:\\New Drive Data\\Project Tester - Cost Manager & Expenser\\graph\\system_graph.json", "source_location": "L6"}], "edges": [{"source": "c_new_drive_data_project_tester_cost_manager_expenser_graph_system_graph_json", "target": "graph_system_graph_ledger", "relation": "contains", "confidence": "EXTRACTED", "source_file": "C:\\New Drive Data\\Project Tester - Cost Manager & Expenser\\graph\\system_graph.json", "source_location": "L2", "weight": 1.0}, {"source": "graph_system_graph_ledger", "target": "ref_wallet", "relation": "extends", "confidence": "EXTRACTED", "source_file": "C:\\New Drive Data\\Project Tester - Cost Manager & Expenser\\graph\\system_graph.json", "source_location": "L2", "weight": 1.0, "context": "import"}, {"source": "c_new_drive_data_project_tester_cost_manager_expenser_graph_system_graph_json", "target": "graph_system_graph_wallet", "relation": "contains", "confidence": "EXTRACTED", "source_file": "C:\\New Drive Data\\Project Tester - Cost Manager & Expenser\\graph\\system_graph.json", "source_location": "L3", "weight": 1.0}, {"source": "graph_system_graph_wallet", "target": "ref_transactions", "relation": "extends", "confidence": "EXTRACTED", "source_file": "C:\\New Drive Data\\Project Tester - Cost Manager & Expenser\\graph\\system_graph.json", "source_location": "L3", "weight": 1.0, "context": "import"}, {"source": "c_new_drive_data_project_tester_cost_manager_expenser_graph_system_graph_json", "target": "graph_system_graph_loans", "relation": "contains", "confidence": "EXTRACTED", "source_file": "C:\\New Drive Data\\Project Tester - Cost Manager & Expenser\\graph\\system_graph.json", "source_location": "L4", "weight": 1.0}, {"source": "graph_system_graph_loans", "target": "ref_payments", "relation": "extends", "confidence": "EXTRACTED", "source_file": "C:\\New Drive Data\\Project Tester - Cost Manager & Expenser\\graph\\system_graph.json", "source_location": "L4", "weight": 1.0, "context": "import"}, {"source": "c_new_drive_data_project_tester_cost_manager_expenser_graph_system_graph_json", "target": "graph_system_graph_analytics", "relation": "contains", "confidence": "EXTRACTED", "source_file": "C:\\New Drive Data\\Project Tester - Cost Manager & Expenser\\graph\\system_graph.json", "source_location": "L5", "weight": 1.0}, {"source": "graph_system_graph_analytics", "target": "ref_ledger", "relation": "extends", "confidence": "EXTRACTED", "source_file": "C:\\New Drive Data\\Project Tester - Cost Manager & Expenser\\graph\\system_graph.json", "source_location": "L5", "weight": 1.0, "context": "import"}, {"source": "graph_system_graph_analytics", "target": "ref_wallet", "relation": "extends", "confidence": "EXTRACTED", "source_file": "C:\\New Drive Data\\Project Tester - Cost Manager & Expenser\\graph\\system_graph.json", "source_location": "L5", "weight": 1.0, "context": "import"}, {"source": "c_new_drive_data_project_tester_cost_manager_expenser_graph_system_graph_json", "target": "graph_system_graph_forecast", "relation": "contains", "confidence": "EXTRACTED", "source_file": "C:\\New Drive Data\\Project Tester - Cost Manager & Expenser\\graph\\system_graph.json", "source_location": "L6", "weight": 1.0}, {"source": "graph_system_graph_forecast", "target": "ref_analytics", "relation": "extends", "confidence": "EXTRACTED", "source_file": "C:\\New Drive Data\\Project Tester - Cost Manager & Expenser\\graph\\system_graph.json", "source_location": "L6", "weight": 1.0, "context": "import"}]}