{"nodes": [{"id": "c_new_drive_data_project_tester_cost_manager_expenser_brain_decisions_log_md", "label": "decisions_log.md", "file_type": "document", "source_file": "C:\\New Drive Data\\Project Tester - Cost Manager & Expenser\\brain\\decisions_log.md", "source_location": "L1"}, {"id": "brain_decisions_log_fcc_engineering_decisions_log", "label": "FCC - Engineering Decisions Log", "file_type": "document", "source_file": "C:\\New Drive Data\\Project Tester - Cost Manager & Expenser\\brain\\decisions_log.md", "source_location": "L1"}, {"id": "brain_decisions_log_dec_001_mobile_application_built_on_flutter", "label": "DEC-001: Mobile Application built on Flutter", "file_type": "document", "source_file": "C:\\New Drive Data\\Project Tester - Cost Manager & Expenser\\brain\\decisions_log.md", "source_location": "L7"}, {"id": "brain_decisions_log_dec_002_offline_first_local_database_via_sqflite", "label": "DEC-002: Offline-First Local Database via `sqflite`", "file_type": "document", "source_file": "C:\\New Drive Data\\Project Tester - Cost Manager & Expenser\\brain\\decisions_log.md", "source_location": "L17"}, {"id": "brain_decisions_log_dec_003_central_state_management_via_provider", "label": "DEC-003: Central State Management via `provider`", "file_type": "document", "source_file": "C:\\New Drive Data\\Project Tester - Cost Manager & Expenser\\brain\\decisions_log.md", "source_location": "L27"}, {"id": "brain_decisions_log_dec_004_interactive_visualization_via_graphify_echarts", "label": "DEC-004: Interactive Visualization via `graphify` (ECharts)", "file_type": "document", "source_file": "C:\\New Drive Data\\Project Tester - Cost Manager & Expenser\\brain\\decisions_log.md", "source_location": "L37"}], "edges": [{"source": "c_new_drive_data_project_tester_cost_manager_expenser_brain_decisions_log_md", "target": "brain_decisions_log_fcc_engineering_decisions_log", "relation": "contains", "confidence": "EXTRACTED", "source_file": "C:\\New Drive Data\\Project Tester - Cost Manager & Expenser\\brain\\decisions_log.md", "source_location": "L1", "weight": 1.0}, {"source": "brain_decisions_log_fcc_engineering_decisions_log", "target": "brain_decisions_log_dec_001_mobile_application_built_on_flutter", "relation": "contains", "confidence": "EXTRACTED", "source_file": "C:\\New Drive Data\\Project Tester - Cost Manager & Expenser\\brain\\decisions_log.md", "source_location": "L7", "weight": 1.0}, {"source": "brain_decisions_log_fcc_engineering_decisions_log", "target": "brain_decisions_log_dec_002_offline_first_local_database_via_sqflite", "relation": "contains", "confidence": "EXTRACTED", "source_file": "C:\\New Drive Data\\Project Tester - Cost Manager & Expenser\\brain\\decisions_log.md", "source_location": "L17", "weight": 1.0}, {"source": "brain_decisions_log_fcc_engineering_decisions_log", "target": "brain_decisions_log_dec_003_central_state_management_via_provider", "relation": "contains", "confidence": "EXTRACTED", "source_file": "C:\\New Drive Data\\Project Tester - Cost Manager & Expenser\\brain\\decisions_log.md", "source_location": "L27", "weight": 1.0}, {"source": "brain_decisions_log_fcc_engineering_decisions_log", "target": "brain_decisions_log_dec_004_interactive_visualization_via_graphify_echarts", "relation": "contains", "confidence": "EXTRACTED", "source_file": "C:\\New Drive Data\\Project Tester - Cost Manager & Expenser\\brain\\decisions_log.md", "source_location": "L37", "weight": 1.0}], "input_tokens": 0, "output_tokens": 0}